Php55WebLingJichujiaochengKaifaYigeZaixianYueduWangzhan/README.md
Php55WebLingJichujiaochengKaifaYigeZaixianYueduWangzhan/__init__.py
Php55WebLingJichujiaochengKaifaYigeZaixianYueduWangzhan/__main__.py
Php55WebLingJichujiaochengKaifaYigeZaixianYueduWangzhan/file.epub
Php55WebLingJichujiaochengKaifaYigeZaixianYueduWangzhan/index.html
Php55WebLingJichujiaochengKaifaYigeZaixianYueduWangzhan/css/__init__.py
Php55WebLingJichujiaochengKaifaYigeZaixianYueduWangzhan/css/annotations.css
Php55WebLingJichujiaochengKaifaYigeZaixianYueduWangzhan/css/main.css
Php55WebLingJichujiaochengKaifaYigeZaixianYueduWangzhan/css/normalize.css
Php55WebLingJichujiaochengKaifaYigeZaixianYueduWangzhan/css/popup.css
Php55WebLingJichujiaochengKaifaYigeZaixianYueduWangzhan/font/__init__.py
Php55WebLingJichujiaochengKaifaYigeZaixianYueduWangzhan/font/fontello.eot
Php55WebLingJichujiaochengKaifaYigeZaixianYueduWangzhan/font/fontello.svg
Php55WebLingJichujiaochengKaifaYigeZaixianYueduWangzhan/font/fontello.ttf
Php55WebLingJichujiaochengKaifaYigeZaixianYueduWangzhan/font/fontello.woff
Php55WebLingJichujiaochengKaifaYigeZaixianYueduWangzhan/img/__init__.py
Php55WebLingJichujiaochengKaifaYigeZaixianYueduWangzhan/img/annotator-glyph-sprite.png
Php55WebLingJichujiaochengKaifaYigeZaixianYueduWangzhan/img/annotator-icon-sprite.png
Php55WebLingJichujiaochengKaifaYigeZaixianYueduWangzhan/img/apple-touch-icon.png
Php55WebLingJichujiaochengKaifaYigeZaixianYueduWangzhan/img/cancelfullscreen.png
Php55WebLingJichujiaochengKaifaYigeZaixianYueduWangzhan/img/close.png
Php55WebLingJichujiaochengKaifaYigeZaixianYueduWangzhan/img/fullscreen.png
Php55WebLingJichujiaochengKaifaYigeZaixianYueduWangzhan/img/loader.gif
Php55WebLingJichujiaochengKaifaYigeZaixianYueduWangzhan/img/menu-icon.png
Php55WebLingJichujiaochengKaifaYigeZaixianYueduWangzhan/img/save.png
Php55WebLingJichujiaochengKaifaYigeZaixianYueduWangzhan/img/saved.png
Php55WebLingJichujiaochengKaifaYigeZaixianYueduWangzhan/img/settings-s.png
php_5_5_web_ling_jichujiaocheng_kaifa_yige_zaixian_yuedu_wangzhan-2024.3.4.0.dist-info/METADATA
php_5_5_web_ling_jichujiaocheng_kaifa_yige_zaixian_yuedu_wangzhan-2024.3.4.0.dist-info/WHEEL
php_5_5_web_ling_jichujiaocheng_kaifa_yige_zaixian_yuedu_wangzhan-2024.3.4.0.dist-info/entry_points.txt
php_5_5_web_ling_jichujiaocheng_kaifa_yige_zaixian_yuedu_wangzhan-2024.3.4.0.dist-info/top_level.txt
php_5_5_web_ling_jichujiaocheng_kaifa_yige_zaixian_yuedu_wangzhan-2024.3.4.0.dist-info/RECORD
